rsstools/__init__.py
rsstools/__main__.py
rsstools/cli.py
rsstools/exceptions.py
rsstools/feed_creator.py
rsstools/feed_validator.py
rsstools/templates.py
rsstools-0.3.1.dist-info/LICENSE
rsstools-0.3.1.dist-info/METADATA
rsstools-0.3.1.dist-info/WHEEL
rsstools-0.3.1.dist-info/entry_points.txt
rsstools-0.3.1.dist-info/top_level.txt
rsstools-0.3.1.dist-info/RECORD
