Metadata-Version: 2.1
Name: rsstools
Version: 0.3.1
Summary: tools for managing rss feeds
Author-email: sctech <gamerselimiko@gmail.com>
Project-URL: source, https://github.com/sctech-tr/rsstools
Keywords: rss,feed,rssfeed,xml,tool,cli,rssxml,atomrss,rssatom,news,atom,rssfeed,rssfeedreader,rssfeedparser,rssfeedgenerator,rssfeedmanager
Classifier: Programming Language :: Python :: 3
Classifier: Programming Language :: Python :: 3.12
Classifier: Programming Language :: Python :: 3.13
Classifier: Programming Language :: Python :: 3.9
Classifier: License :: OSI Approved :: GNU General Public License v3 or later (GPLv3+)
Classifier: Operating System :: OS Independent
Requires-Python: >=3.9
License-File: LICENSE
Requires-Dist: click
